{
  "term": "Fall",
  "year": "2021",
  "level": [],
  "topics": [],
  "legacy_uid": "",
  "instructors": {
    "content": [],
    "website": "magic-science-and-religion"
  },
  "course_image": {
    "content": "",
    "website": "magic-science-and-religion"
  },
  "course_title": "Magic, Science, and Religion",
  "course_description": "",
  "department_numbers": [
    "21A"
  ],
  "extra_course_numbers": "",
  "primary_course_number": "21A.520",
  "course_image_thumbnail": {
    "content": "",
    "website": "magic-science-and-religion"
  },
  "learning_resource_types": [],
  "site_uid": "bbb4695f-20a6-442d-a7a4-6a8d518c3a91"
}